zeroscratches/__init__.py
zeroscratches/erase_scratches.py
zeroscratches/erasescratches/__init__.py
zeroscratches/erasescratches/options.py
zeroscratches/erasescratches/models/NonLocal_feature_mapping_model.py
zeroscratches/erasescratches/models/__init__.py
zeroscratches/erasescratches/models/base_model.py
zeroscratches/erasescratches/models/mapping_model.py
zeroscratches/erasescratches/models/networks.py
zeroscratches/maskscratches/__init__.py
zeroscratches/maskscratches/scratches_detector.py
zeroscratches/maskscratches/detection_models/__init__.py
zeroscratches/maskscratches/detection_models/antialiasing.py
zeroscratches/maskscratches/detection_models/networks.py
zeroscratches/maskscratches/detection_models/Synchronized-BatchNorm-PyTorch/__init__.py
zeroscratches/maskscratches/detection_models/Synchronized-BatchNorm-PyTorch/sync_batchnorm/__init__.py
zeroscratches/maskscratches/detection_models/Synchronized-BatchNorm-PyTorch/sync_batchnorm/batchnorm.py
zeroscratches/maskscratches/detection_models/Synchronized-BatchNorm-PyTorch/sync_batchnorm/batchnorm_reimpl.py
zeroscratches/maskscratches/detection_models/Synchronized-BatchNorm-PyTorch/sync_batchnorm/comm.py
zeroscratches/maskscratches/detection_models/Synchronized-BatchNorm-PyTorch/sync_batchnorm/replicate.py
zeroscratches/maskscratches/detection_models/Synchronized-BatchNorm-PyTorch/sync_batchnorm/unittest.py
zeroscratches/maskscratches/detection_models/Synchronized-BatchNorm-PyTorch/tests/__init__.py
zeroscratches/maskscratches/detection_models/Synchronized-BatchNorm-PyTorch/tests/test_numeric_batchnorm.py
zeroscratches/maskscratches/detection_models/Synchronized-BatchNorm-PyTorch/tests/test_numeric_batchnorm_v2.py
zeroscratches/maskscratches/detection_models/Synchronized-BatchNorm-PyTorch/tests/test_sync_batchnorm.py
zeroscratches/maskscratches/detection_models/sync_batchnorm/__init__.py
zeroscratches/maskscratches/detection_models/sync_batchnorm/batchnorm.py
zeroscratches-1.0.2.dist-info/LICENSE
zeroscratches-1.0.2.dist-info/METADATA
zeroscratches-1.0.2.dist-info/WHEEL
zeroscratches-1.0.2.dist-info/entry_points.txt
zeroscratches-1.0.2.dist-info/top_level.txt
zeroscratches-1.0.2.dist-info/RECORD
